lu_vp_detect/__init__.py
lu_vp_detect/__version__.py
lu_vp_detect/run_vp_detect.py
lu_vp_detect/vp_detection.py
lu_vp_detect-1.0.4.dist-info/LICENSE
lu_vp_detect-1.0.4.dist-info/METADATA
lu_vp_detect-1.0.4.dist-info/WHEEL
lu_vp_detect-1.0.4.dist-info/entry_points.txt
lu_vp_detect-1.0.4.dist-info/top_level.txt
lu_vp_detect-1.0.4.dist-info/RECORD
