Metadata-Version: 2.1
Name: lu-vp-detect
Version: 1.0.4
Summary: Xiaohu Lu's Vanishing Point Detection algorithm
Home-page: https://github.com/rayryeng/XiaohuLuVPDetection
Author: Ray Phan
Author-email: rphan@ryerson.ca
License: MIT
Classifier: License :: OSI Approved :: MIT License
Classifier: Programming Language :: Python
Classifier: Programming Language :: Python :: 3.8
Classifier: Programming Language :: Python :: 3.9
Classifier: Programming Language :: Python :: 3.10
Classifier: Programming Language :: Python :: 3.11
Classifier: Programming Language :: Python :: Implementation :: PyPy
Requires-Python: >= 3.8
License-File: LICENSE
Requires-Dist: numpy
Requires-Dist: opencv-contrib-python
